emojicrypt/__init__.py
emojicrypt/emojicrypt.py
emojicrypt/emojify.py
emojicrypt/main.py
emojicrypt-1.0.2.dist-info/METADATA
emojicrypt-1.0.2.dist-info/WHEEL
emojicrypt-1.0.2.dist-info/top_level.txt
emojicrypt-1.0.2.dist-info/RECORD
