Metadata-Version: 2.1
Name: emojicrypt
Version: 1.0.2
Summary: AES encryption encoded using emojis
Home-page: https://github.com/InputBlackBoxOutput/EmojiCrypt
Author: Rutuparn Pawar
Author-email: rutuparn.17U253@viit.ac.in
License: UNKNOWN
Keywords: emojis,encoding,AES,encryption
Platform: UNKNOWN
Classifier: Environment :: Console
Classifier: Intended Audience :: Developers
Classifier: Programming Language :: Python :: 3
Requires-Dist: pycryptodome (==3.10.1)
